{
    "version": 1.0,
    "type": "ItemInfo",
    "items": {
        "wood": {
            "name": "Wood pile",
            "size": "1,1",
            "spriteID": 0,
            "consumable": false
        },
        "berryRed": {
            "name": "Raspberry",
            "size": "1,1",
            "spriteID": 1,
            "consumable": true
        },
        "berryBlue": {
            "name": "Blueberry",
            "size": "1,1",
            "spriteID": 2,
            "consumable": true
        },
        "stone": {
            "name": "Stone",
            "size": "1,1",
            "spriteID": 3,
            "consumable": false
        },
    }
}